deplock/exceptions.py
deplock/configs/_validators.py
deplock/configs/base.py
deplock/configs/packages.py
deplock/configs/uv_lock.py
deplock/parser/poetry_class.py
deplock/parser/pylock.py
deplock/parser/uv.py
deplock/types/environment.py
deplock/types/requirement.py
deplock/utils/markers.py
deplock/utils/prebuilt_envs.py
deplock-0.1.1.dist-info/METADATA
deplock-0.1.1.dist-info/WHEEL
deplock-0.1.1.dist-info/licenses/LICENSE
deplock-0.1.1.dist-info/RECORD
