Metadata-Version: 2.4
Name: deplock
Version: 0.1.1
Project-URL: repository, https://github.com/block/deplock
Author-email: Tyler Zupan <tzupan@squareup.com>, Josh Hamet <jhamet@squareup.com>
License-File: LICENSE
Requires-Python: >=3.10
Requires-Dist: poetry>=2.1.3
Requires-Dist: pydantic>=2.11.7
Requires-Dist: tomlkit>=0.13.3
